ptfuzzmenu/__init__.py
ptfuzzmenu-0.1.2.data/data/share/doc/python-ptfuzzmenu/AUTHORS
ptfuzzmenu-0.1.2.data/data/share/doc/python-ptfuzzmenu/LICENSE
ptfuzzmenu-0.1.2.data/data/share/doc/python-ptfuzzmenu/README.md
ptfuzzmenu-0.1.2.dist-info/LICENSE
ptfuzzmenu-0.1.2.dist-info/METADATA
ptfuzzmenu-0.1.2.dist-info/WHEEL
ptfuzzmenu-0.1.2.dist-info/top_level.txt
ptfuzzmenu-0.1.2.dist-info/RECORD
